notary/__init__.py
notary/validator.py
data_notary-0.3.0.dist-info/LICENSE
data_notary-0.3.0.dist-info/METADATA
data_notary-0.3.0.dist-info/WHEEL
data_notary-0.3.0.dist-info/top_level.txt
data_notary-0.3.0.dist-info/RECORD
